avwx_swift/__about__.py
avwx_swift/__init__.py
avwx_swift/fil.py
avwx_swift/jms.py
avwx_swift/message.py
avwx_swift/notam.py
avwx_swift-0.1.0.dev0.dist-info/METADATA
avwx_swift-0.1.0.dev0.dist-info/WHEEL
avwx_swift-0.1.0.dev0.dist-info/licenses/LICENSE
avwx_swift-0.1.0.dev0.dist-info/RECORD
