Metadata-Version: 2.4
Name: avwx-swift
Version: 0.1.0.dev0
Summary: Python connector for the FAA SWIFT data information system
Project-URL: Issues, https://github.com/avwx-rest/avwx-swift/issues
Project-URL: Source, https://github.com/avwx-rest/avwx-swift
Author-email: Michael duPont <michael@dupont.dev>
License-Expression: MIT
License-File: LICENSE
Keywords: aviation,faa,notam,swift,weather
Requires-Python: >=3.12
Requires-Dist: geojson~=3.2
Requires-Dist: solace-pubsubplus~=1.10
Requires-Dist: xmltodict~=0.14.2
